starlette_responses_kit/__init__.py
starlette_responses_kit/file.py
starlette_responses_kit-0.1.0.dist-info/METADATA
starlette_responses_kit-0.1.0.dist-info/WHEEL
starlette_responses_kit-0.1.0.dist-info/licenses/LICENSE
starlette_responses_kit-0.1.0.dist-info/RECORD
